{
    "roll_upper_arm": [
        0.0, 
        0.0, 
        0.0, 
        0.0, 
        0.0, 
        0.0, 
        0.0, 
        0.0, 
        0.0, 
        0.0, 
        0.0, 
        0.0, 
        0.0, 
        0.0, 
        0.0, 
        0.0, 
        0.0, 
        0.0, 
        0.0, 
        0.0, 
        0.0, 
        0.0, 
        0.0, 
        0.0, 
        0.0, 
        0.0, 
        0.0, 
        0.0, 
        0.0, 
        0.0, 
        0.0, 
        0.0, 
        0.0, 
        0.0, 
        0.0
    ], 
    "emg_chest": [
        1023, 
        1023, 
        1023, 
        1023, 
        1023, 
        67, 
        71, 
        67, 
        140, 
        107, 
        327, 
        260, 
        871, 
        404, 
        233, 
        154, 
        108, 
        82, 
        70, 
        68, 
        322, 
        352, 
        578, 
        1023, 
        1023, 
        1023, 
        1023, 
        1023, 
        1023, 
        1023, 
        1023, 
        1023, 
        1023, 
        1023, 
        1023
    ], 
    "pitch_upper_arm": [
        0.0, 
        0.0, 
        0.0, 
        0.0, 
        0.0, 
        0.0, 
        0.0, 
        0.0, 
        0.0, 
        0.0, 
        0.0, 
        0.0, 
        0.0, 
        0.0, 
        0.0, 
        0.0, 
        0.0, 
        0.0, 
        0.0, 
        0.0, 
        0.0, 
        0.0, 
        0.0, 
        0.0, 
        0.0, 
        0.0, 
        0.0, 
        0.0, 
        0.0, 
        0.0, 
        0.0, 
        0.0, 
        0.0, 
        0.0, 
        0.0
    ], 
    "emg_upper_arm": [
        482, 
        675, 
        772, 
        906, 
        627, 
        674, 
        911, 
        851, 
        744, 
        613, 
        397, 
        234, 
        192, 
        182, 
        280, 
        364, 
        578, 
        900, 
        836, 
        713, 
        404, 
        277, 
        515, 
        1011, 
        1023, 
        1023, 
        807, 
        365, 
        414, 
        168, 
        417, 
        694, 
        536, 
        512, 
        359
    ], 
    "roll_forearm": [
        -69.35, 
        -69.87, 
        -71.73, 
        -72.39, 
        -73.65, 
        -66.95, 
        -65.22, 
        -69.29, 
        -64.04, 
        -53.05, 
        -45.08, 
        -56.48, 
        -50.78, 
        -60.81, 
        -66.2, 
        -64.4, 
        -62.85, 
        -65.88, 
        -75.44, 
        -60.59, 
        -57.15, 
        -60.68, 
        -52.97, 
        -64.97, 
        -64.53, 
        -65.0, 
        -40.77, 
        -57.83, 
        -58.12, 
        -72.69, 
        -60.59, 
        -62.36, 
        -71.33, 
        -74.09, 
        -68.83
    ], 
    "pitch_forearm": [
        -7.75, 
        -6.29, 
        -8.69, 
        -10.1, 
        -11.28, 
        -11.89, 
        -13.78, 
        -7.98, 
        -7.08, 
        -28.56, 
        -44.88, 
        -33.43, 
        -39.19, 
        -29.15, 
        -21.9, 
        -25.6, 
        -26.59, 
        -24.01, 
        -14.41, 
        -28.91, 
        -32.33, 
        -25.63, 
        -29.02, 
        -24.98, 
        -25.03, 
        -22.77, 
        -46.86, 
        9.28, 
        -5.39, 
        -7.33, 
        -13.89, 
        -17.36, 
        -11.66, 
        -10.79, 
        -16.17
    ], 
    "emg_forearm": [
        1015, 
        919, 
        898, 
        872, 
        611, 
        129, 
        147, 
        152, 
        211, 
        287, 
        246, 
        397, 
        306, 
        442, 
        287, 
        226, 
        196, 
        236, 
        318, 
        388, 
        393, 
        463, 
        580, 
        436, 
        384, 
        387, 
        367, 
        395, 
        620, 
        1004, 
        1023, 
        1023, 
        1023, 
        1023, 
        1023
    ]
}